cda/__init__.py
cda/aid_info.py
cda/college_evaluation.py
cda/college_info.py
cda/cost_info.py
cda/dataset_info.py
cda/student_info.py
cda/college_scorecard/__init__.py
cda/college_scorecard/_data_processing.py
cda/college_scorecard/api.py
cda/college_scorecard/data_processing.py
cda-0.1.1.dist-info/LICENSE
cda-0.1.1.dist-info/METADATA
cda-0.1.1.dist-info/WHEEL
cda-0.1.1.dist-info/top_level.txt
cda-0.1.1.dist-info/RECORD
