Metadata-Version: 2.1
Name: cda
Version: 0.1.1
Summary: College Data Analysis
Home-page: https://github.com/alisoltanirad/CDA
Author: Ali Soltani Rad
Author-email: soltaniradali@gmail.com
License: UNKNOWN
Platform: UNKNOWN
Classifier: Programming Language :: Python :: 3
Classifier: License :: OSI Approved :: MIT License
Classifier: Operating System :: OS Independent
Requires-Python: >=3.7
